LICENSE.txt
MANIFEST.in
README.txt
setup.py
pcart_people/__init__.py
pcart_people/admin.py
pcart_people/apps.py
pcart_people/cms_apps.py
pcart_people/models.py
pcart_people/urls.py
pcart_people/views.py
pcart_people.egg-info/PKG-INFO
pcart_people.egg-info/SOURCES.txt
pcart_people.egg-info/dependency_links.txt
pcart_people.egg-info/not-zip-safe
pcart_people.egg-info/requires.txt
pcart_people.egg-info/top_level.txt
pcart_people/migrations/0001_initial.py
pcart_people/migrations/0002_auto_20170723_1838.py
pcart_people/migrations/0003_auto_20170723_1939.py
pcart_people/migrations/__init__.py
pcart_people/templates/people/people.html